doctor/__init__.py
doctor/_version.py
doctor/constants.py
doctor/errors.py
doctor/flask.py
doctor/parsers.py
doctor/resource.py
doctor/response.py
doctor/routing.py
doctor/schema.py
doctor/types.py
doctor/docs/__init__.py
doctor/docs/base.py
doctor/docs/flask.py
doctor/utils/__init__.py
doctor-3.13.0.dist-info/LICENSE
doctor-3.13.0.dist-info/METADATA
doctor-3.13.0.dist-info/WHEEL
doctor-3.13.0.dist-info/top_level.txt
doctor-3.13.0.dist-info/RECORD
